setup.cfg
setup.py
cycli/__init__.py
cycli/binder.py
cycli/buffer.py
cycli/completer.py
cycli/cypher.py
cycli/driver.py
cycli/main.py
cycli/markov.py
cycli/style.py
cycli/table.py
cycli.egg-info/PKG-INFO
cycli.egg-info/SOURCES.txt
cycli.egg-info/dependency_links.txt
cycli.egg-info/entry_points.txt
cycli.egg-info/not-zip-safe
cycli.egg-info/requires.txt
cycli.egg-info/top_level.txt