Metadata-Version: 1.0
Name: cycli
Version: 0.7.2
Summary: A Command Line Interface for Cypher.
Home-page: https://github.com/nicolewhite/cycli
Author: Nicole White
Author-email: nicole@neo4j.com
License: MIT
Keywords: neo4j cypher cli syntax autocomplete
Platform: UNKNOWN
